MANIFEST.in
README.rst
repocheck_binsym.py
setup.py
repochecker_binsym/__init__.py
repochecker_binsym/logger.py
repochecker_binsym/storage.py
repochecker_binsym.egg-info/PKG-INFO
repochecker_binsym.egg-info/SOURCES.txt
repochecker_binsym.egg-info/dependency_links.txt
repochecker_binsym.egg-info/not-zip-safe
repochecker_binsym.egg-info/requires.txt
repochecker_binsym.egg-info/top_level.txt