Metadata-Version: 1.1
Name: repochecker-binsym
Version: 0.9.4
Summary: Repository checker that validates completeness of a linux repository over binary symbols
Home-page: https://abf.io/gluk47/repochecker_binsym
Author: Rosa labs & HSE
Author-email: gluk47@gmail.com
License: UNKNOWN
Platform: UNKNOWN
Classifier: Development Status :: 4 - Beta
Classifier: Environment :: Console
Classifier: License :: OSI Approved :: GNU General Public License v3 (GPLv3)
Classifier: Natural Language :: English
Classifier: Operating System :: POSIX :: Linux
Classifier: Programming Language :: Python :: 2
Classifier: Topic :: System :: Software Distribution
Classifier: Topic :: Utilities
